fragment_api/__init__.py
fragment_api/client.py
starsgraceapi-1.0.0.dist-info/LICENSE
starsgraceapi-1.0.0.dist-info/METADATA
starsgraceapi-1.0.0.dist-info/WHEEL
starsgraceapi-1.0.0.dist-info/top_level.txt
starsgraceapi-1.0.0.dist-info/RECORD
