Metadata-Version: 2.2
Name: starsgraceAPI
Version: 1.0.0
Summary: Python client for the Fragment API
Home-page: https://github.com/starsgrace-api/FragmentAPI
Author: StarsGrace
Author-email: bashirsandking@gmail.com
License: MIT
Keywords: fragment api telegram stars premium ton
Classifier: Programming Language :: Python :: 3
Classifier: License :: OSI Approved :: MIT License
Classifier: Operating System :: OS Independent
Requires-Python: >=3.7
License-File: LICENSE
Requires-Dist: requests>=2.28.0
Dynamic: author
Dynamic: author-email
Dynamic: classifier
Dynamic: description
Dynamic: description-content-type
Dynamic: home-page
Dynamic: keywords
Dynamic: license
Dynamic: requires-dist
Dynamic: requires-python
Dynamic: summary
